<?xml version="1.0" encoding="UTF-8"?><record_update>
    <sys_choice action="DELETE" field="u_what_needed" table="x_58872_needit_needit" version="3">
        <sys_choice_set action="DELETE">
            <element>u_what_needed</element>
            <name>x_58872_needit_needit</name>
            <sys_class_name/>
            <sys_created_by/>
            <sys_created_on/>
            <sys_id/>
            <sys_mod_count/>
            <sys_name/>
            <sys_package/>
            <sys_policy/>
            <sys_scope/>
            <sys_update_name/>
            <sys_updated_by/>
            <sys_updated_on>2020-06-18 02:56:09</sys_updated_on>
        </sys_choice_set>
    </sys_choice>
    <sys_update_version action="INSERT_OR_UPDATE">
        <action>DELETE</action>
        <application/>
        <file_path/>
        <instance_id>61ae6e8fdbaa13004f035d00cf961928</instance_id>
        <instance_name>dev60907</instance_name>
        <name>sys_choice_x_58872_needit_needit_u_what_needed</name>
        <payload><![CDATA[<?xml version="1.0" encoding="UTF-8"?><record_update><sys_choice action="DELETE" field="u_what_needed" table="x_58872_needit_needit" version="3"><sys_choice_set action="DELETE"><element>u_what_needed</element><name>x_58872_needit_needit</name><sys_class_name/><sys_created_by/><sys_created_on/><sys_id/><sys_mod_count/><sys_name/><sys_package/><sys_policy/><sys_scope/><sys_update_name/><sys_updated_by/><sys_updated_on>2020-06-18 02:56:09</sys_updated_on></sys_choice_set></sys_choice></record_update>]]></payload>
        <payload_hash>-429457270</payload_hash>
        <record_name>x_58872_needit_needit.u_what_needed</record_name>
        <reverted_from/>
        <source>c13e93e3dbcd10109446f36f299619b9</source>
        <source_table>sys_update_set</source_table>
        <state>previous</state>
        <sys_created_by>admin</sys_created_by>
        <sys_created_on>2020-06-18 02:56:09</sys_created_on>
        <sys_id>58de56d8db6910109446f36f29961977</sys_id>
        <sys_mod_count>0</sys_mod_count>
        <sys_recorded_at>172c55ae9bf0000001</sys_recorded_at>
        <sys_updated_by>admin</sys_updated_by>
        <sys_updated_on>2020-06-18 02:56:09</sys_updated_on>
        <type>Choice list</type>
        <update_guid>d0de56d801691010c8249ca008017977</update_guid>
        <update_guid_history>d0de56d801691010c8249ca008017977:-429457270,9cde56d8d6691010cc6490ad9b04d273:-356377995,1cde56d87c6910106f78b718ab531c70:1008369778,98de56d879691010d3734f0d06127d6d:1793394304,18de56d87b6910102d2024326ca7d76a:60889329,84de56d8a6691010b761d78fa9187967:-334244309,04de56d81e691010a8829638dea7f964:-1795993788,80de56d8726910102db474018c124361:1989655492,d5736196ae511010e56d794fcb06d379:25275431</update_guid_history>
    </sys_update_version>
    <sys_metadata_delete action="INSERT_OR_UPDATE">
        <sys_audit_delete/>
        <sys_class_name>sys_metadata_delete</sys_class_name>
        <sys_created_by>admin</sys_created_by>
        <sys_created_on>2020-06-18 02:56:19</sys_created_on>
        <sys_db_object display_value="" name="sys_choice_set">sys_choice_set</sys_db_object>
        <sys_id>1aded6d8db6910109446f36f299619cc</sys_id>
        <sys_metadata>1aded6d8db6910109446f36f299619cc</sys_metadata>
        <sys_mod_count>0</sys_mod_count>
        <sys_name>u_what_needed</sys_name>
        <sys_package display_value="NeedIt" source="x_58872_needit">6ead8e780f603200cd674f8ce1050ed1</sys_package>
        <sys_parent/>
        <sys_policy/>
        <sys_scope display_value="NeedIt">6ead8e780f603200cd674f8ce1050ed1</sys_scope>
        <sys_scope_delete display_value="">94872a8897db403e8ee69a431de2fca4</sys_scope_delete>
        <sys_update_name>sys_choice_x_58872_needit_needit_u_what_needed</sys_update_name>
        <sys_update_version display_value="sys_choice_x_58872_needit_needit_u_what_needed">58de56d8db6910109446f36f29961977</sys_update_version>
        <sys_updated_by>admin</sys_updated_by>
        <sys_updated_on>2020-06-18 02:56:19</sys_updated_on>
    </sys_metadata_delete>
</record_update>
